tronapihelper/__init__.py
tronapihelper-0.1.0.dist-info/licenses/LICENSE
tronapihelper-0.1.0.dist-info/METADATA
tronapihelper-0.1.0.dist-info/WHEEL
tronapihelper-0.1.0.dist-info/top_level.txt
tronapihelper-0.1.0.dist-info/RECORD
